LICENSE
MANIFEST.in
README.rst
setup.py
sofart/__init__.py
sofart/collection.py
sofart/database.py
sofart/exceptions.py
sofart/logger.py
sofart/operators.py
sofart.egg-info/PKG-INFO
sofart.egg-info/SOURCES.txt
sofart.egg-info/dependency_links.txt
sofart.egg-info/requires.txt
sofart.egg-info/top_level.txt
sofart/serializers/__init__.py
sofart/serializers/_json.py
sofart/serializers/_msgpack.py
sofart/serializers/_pickle.py