Metadata-Version: 1.1
Name: sofart
Version: 0.3.6
Summary: Python in-memory embedded and non-relationnal database
Home-page: UNKNOWN
Author: toxinu
Author-email: toxinu@gmail.com
License: Copyright (c) 2020, toxinu
